README.rst
setup.cfg
setup.py
paotung/__int__.py
paotung/ppaotung.py
paotung.egg-info/PKG-INFO
paotung.egg-info/SOURCES.txt
paotung.egg-info/dependency_links.txt
paotung.egg-info/top_level.txt