Metadata-Version: 1.1
Name: paotung
Version: 0.0.1
Summary: Who is Paotung
Home-page: https://github.com/Patcharaporn2093
Author: Patcharaporn
Author-email: patcharaporn.online63@gmail.com
License: MIT
Download-URL: https://github.com/Patcharaporn2093
Keywords: Paotung,ASCII ART,Cat
Platform: UNKNOWN
Classifier: Development Status :: 3 - Alpha
Classifier: Intended Audience :: Education
Classifier: Topic :: Utilities
Classifier: License :: OSI Approved :: MIT License
Classifier: Programming Language :: Python :: 3
Classifier: Programming Language :: Python :: 3.4
Classifier: Programming Language :: Python :: 3.5
Classifier: Programming Language :: Python :: 3.6
Classifier: Programming Language :: Python :: 3.7
Classifier: Programming Language :: Python :: 3.8
Classifier: Programming Language :: Python :: 3.9
Classifier: Programming Language :: Python :: 3.10
